productivity/__init__.py
productivity/driver.py
productivity/mock.py
productivity/util.py
productivity-0.13.0.dist-info/LICENSE
productivity-0.13.0.dist-info/METADATA
productivity-0.13.0.dist-info/WHEEL
productivity-0.13.0.dist-info/entry_points.txt
productivity-0.13.0.dist-info/top_level.txt
productivity-0.13.0.dist-info/RECORD
