Metadata-Version: 2.1
Name: productivity
Version: 0.13.0
Summary: Python driver for AutomationDirect Productivity Series PLCs.
Author-email: Pat Fuller <patrickfuller@gmail.com>
Maintainer-email: Alex Ruddick <alex@ruddick.tech>
Project-URL: Homepage, https://github.com/alexrudd2/productivity
Project-URL: Issues, https://github.com/alexrudd2/productivity/issues
Classifier: License :: OSI Approved :: GNU General Public License v2 (GPLv2)
Classifier: Development Status :: 4 - Beta
Classifier: Natural Language :: English
Classifier: Programming Language :: Python
Classifier: Programming Language :: Python :: 3
Classifier: Programming Language :: Python :: 3.9
Classifier: Programming Language :: Python :: 3.10
Classifier: Programming Language :: Python :: 3.11
Classifier: Programming Language :: Python :: 3.12
Classifier: Programming Language :: Python :: 3.13
Classifier: Topic :: Scientific/Engineering :: Human Machine Interfaces
Classifier: Topic :: Scientific/Engineering :: Electronic Design Automation (EDA)
License-File: LICENSE
Requires-Dist: pyYAML
Requires-Dist: pymodbus >=2.4.0 ; python_version == "3.8"
Requires-Dist: pymodbus >=2.4.0 ; python_version == "3.9"
Requires-Dist: pymodbus <3.8.0,>=3.0.2 ; python_version >= "3.10"
Provides-Extra: test
Requires-Dist: mypy ==1.11.2 ; extra == 'test'
Requires-Dist: pytest ; extra == 'test'
Requires-Dist: pytest-cov ; extra == 'test'
Requires-Dist: pytest-asyncio ; extra == 'test'
Requires-Dist: ruff ==0.6.8 ; extra == 'test'
Requires-Dist: types-PyYAML ; extra == 'test'
